[{"id":1,"ok":"＼(^o^)／","work_time":1800,"run_time":0.000295},{"id":2,"ok":"＼(^o^)／","work_time":1800,"run_time":8.0e-06},{"id":3,"ok":"＼(^o^)／","work_time":1800,"run_time":0.000195},{"id":4,"ok":"＼(^o^)／","work_time":1800,"run_time":0.004598},{"id":5,"ok":"＼(^o^)／","work_time":1800,"run_time":7.0e-06},{"id":6,"ok":"＼(^o^)／","work_time":1800,"run_time":3.7e-05},{"id":7,"ok":"＼(^o^)／","work_time":1800,"run_time":1.411163},{"id":8,"ok":"＼(^o^)／","work_time":1800,"run_time":0.003921},{"id":9,"ok":"＼(^o^)／","work_time":1800,"run_time":0.031491},{"id":10,"ok":"＼(^o^)／","work_time":1800,"run_time":0.304924},{"id":11,"ok":"＼(^o^)／","work_time":1800,"run_time":0.004234},{"id":12,"ok":"＼(^o^)／","work_time":1800,"run_time":1.94128},{"id":13,"ok":"＼(^o^)／","work_time":1800,"run_time":0.000284},{"id":14,"ok":"＼(^o^)／","work_time":1800,"run_time":5.474339}]